monitoring_utils/CHANGELOG.md
monitoring_utils/CONTRIBUTORS.md
monitoring_utils/LICENSE
monitoring_utils/README.md
monitoring_utils/__init__.py
monitoring_utils/Checks/__init__.py
monitoring_utils/Checks/DNS/DNSSECStatus.py
monitoring_utils/Checks/DNS/SPF.py
monitoring_utils/Checks/DNS/__init__.py
monitoring_utils/Checks/Firewall/UFWStatus.py
monitoring_utils/Checks/Firewall/__init__.py
monitoring_utils/Checks/NMAP/Ciphers.py
monitoring_utils/Checks/NMAP/OpenPorts.py
monitoring_utils/Checks/NMAP/__init__.py
monitoring_utils/Checks/NMAP/Scripts/SSLEnumCiphers.py
monitoring_utils/Checks/NMAP/Scripts/__init__.py
monitoring_utils/Checks/OS/RebootRequired.py
monitoring_utils/Checks/OS/__init__.py
monitoring_utils/Checks/SNMP/__init__.py
monitoring_utils/Checks/SNMP/PowerNet_MIB/BatteryBadBatteryPacks.py
monitoring_utils/Checks/SNMP/PowerNet_MIB/BatteryCapacity.py
monitoring_utils/Checks/SNMP/PowerNet_MIB/BatteryPacksAttached.py
monitoring_utils/Checks/SNMP/PowerNet_MIB/BatteryRemainingRuntime.py
monitoring_utils/Checks/SNMP/PowerNet_MIB/BatteryReplacement.py
monitoring_utils/Checks/SNMP/PowerNet_MIB/BatteryStatus.py
monitoring_utils/Checks/SNMP/PowerNet_MIB/BatteryTemperature.py
monitoring_utils/Checks/SNMP/PowerNet_MIB/DiagnosticTestResult.py
monitoring_utils/Checks/SNMP/PowerNet_MIB/LastDiagnosticTestResultTime.py
monitoring_utils/Checks/SNMP/PowerNet_MIB/__init__.py
monitoring_utils/Checks/SNMP/Synology/CPUFanStatus.py
monitoring_utils/Checks/SNMP/Synology/DiskTemperature.py
monitoring_utils/Checks/SNMP/Synology/GPUInfo.py
monitoring_utils/Checks/SNMP/Synology/PowerStatus.py
monitoring_utils/Checks/SNMP/Synology/RAIDStatus.py
monitoring_utils/Checks/SNMP/Synology/SMART.py
monitoring_utils/Checks/SNMP/Synology/ServiceRunning.py
monitoring_utils/Checks/SNMP/Synology/ServiceUsed.py
monitoring_utils/Checks/SNMP/Synology/SpaceIO.py
monitoring_utils/Checks/SNMP/Synology/StorageIO.py
monitoring_utils/Checks/SNMP/Synology/SystemStatus.py
monitoring_utils-2.2.0.post3.dist-info/LICENSE
monitoring_utils-2.2.0.post3.dist-info/METADATA
monitoring_utils-2.2.0.post3.dist-info/WHEEL
monitoring_utils-2.2.0.post3.dist-info/top_level.txt
monitoring_utils-2.2.0.post3.dist-info/RECORD
