Metadata-Version: 2.1
Name: monitoring-utils
Version: 2.2.0.post3
Summary: Utilities for monitoring scripts, plugins and other
Home-page: https://github.com/f-froehlich/monitoring-utils
Author: Fabian Fröhlich
Author-email: mail@confgen.org
License: AGPLv3
Download-URL: https://pypi.org/project/monitoring-utils/
Keywords: icinga,icinga2,icinga2-plugin,monitoring,check,nagios,nagios-plugin,nrpe,healthcheck,serverstatus,security,security-tools
Platform: UNKNOWN
